visualfailureanalysis/__init__.py
visualfailureanalysis/analyser.py
visualfailureanalysis/utils/__init__.py
visualfailureanalysis/utils/utils.py
visualfailureanalysis-0.1.1.dist-info/LICENSE
visualfailureanalysis-0.1.1.dist-info/WHEEL
visualfailureanalysis-0.1.1.dist-info/METADATA
visualfailureanalysis-0.1.1.dist-info/RECORD
