Metadata-Version: 2.1
Name: visualfailureanalysis
Version: 0.1.1
Summary: Toolkit to visualize the reasoning of image classification networks.
License: MIT
Author: Levin Kobelke
Author-email: levin-kobelke@t-online.de
Requires-Python: >=3.9,<4.0
Classifier: License :: OSI Approved :: MIT License
Classifier: Programming Language :: Python :: 3
Classifier: Programming Language :: Python :: 3.9
Classifier: Programming Language :: Python :: 3.10
Classifier: Programming Language :: Python :: 3.11
Requires-Dist: Flask (>=2.2.2,<3.0.0)
Requires-Dist: Pillow (>=9.3.0,<10.0.0)
Requires-Dist: PyPDF2 (>=2.11.2,<3.0.0)
Requires-Dist: albumentations (>=1.3.0,<2.0.0)
Requires-Dist: dash (>=2.7.0,<3.0.0)
Requires-Dist: dash-bootstrap-components (>=1.2.1,<2.0.0)
Requires-Dist: ipywidgets (>=8.0.2,<9.0.0)
Requires-Dist: kaleido (==0.2.1)
Requires-Dist: matplotlib (>=3.6.2,<4.0.0)
Requires-Dist: numpy (>=1.23.5,<2.0.0)
Requires-Dist: pandas (>=1.5.2,<2.0.0)
Requires-Dist: plotly (>=5.11.0,<6.0.0)
Requires-Dist: scikit-learn (>=1.1.3,<2.0.0)
Requires-Dist: scipy (>=1.9.3,<2.0.0)
Requires-Dist: torchvision (>=0.14.0,<0.15.0)
